setup.py
dsplice/__init__.py
dsplice/cli.py
dsplice/version.py
dsplice.egg-info/PKG-INFO
dsplice.egg-info/SOURCES.txt
dsplice.egg-info/dependency_links.txt
dsplice.egg-info/entry_points.txt
dsplice.egg-info/pbr.json
dsplice.egg-info/requires.txt
dsplice.egg-info/top_level.txt