Metadata-Version: 1.1
Name: dsplice
Version: 0.2
Summary: Docker image merge tool
Home-page: https://github.com/bcicen/dsplice
Author: Bradley Cicenas
Author-email: bradley@vektor.nyc
License: http://opensource.org/licenses/MIT
Keywords: docker image merge devops
Platform: UNKNOWN
Classifier: License :: OSI Approved :: MIT License 
Classifier: Natural Language :: English
Classifier: Programming Language :: Python
Classifier: Programming Language :: Python :: 2
Classifier: Programming Language :: Python :: 3
